{"$schema":"https://json-schema.org/draft/2020-12/schema","$id":"td613.flowcore.transfer-encounter/v0.1","title":"TD613 Flow-Core Transfer Encounter","type":"object","additionalProperties":false,"required":["schema","transfer_id","origin_transition_reference","new_context","shared_relation_candidate","observable_correspondence","alternative_explanations","abstention_conditions","system_claim","forbidden_claims","station_owner","authority","closure"],"properties":{"schema":{"const":"td613.flowcore.transfer-encounter/v0.1"},"transfer_id":{"type":"string","pattern":"^flowped_transfer_[a-f0-9]{24}$"},"origin_transition_reference":{"type":"string","pattern":"^flowped_tx_[a-f0-9]{24}$"},"new_context":{"type":"object"},"shared_relation_candidate":{"type":"string","minLength":1},"observable_correspondence":{"type":"array","minItems":1,"items":{"type":"string"}},"alternative_explanations":{"type":"array","minItems":1,"items":{"type":"string"}},"abstention_conditions":{"type":"array","minItems":1,"items":{"type":"string"}},"system_claim":{"const":"pattern-relation-observed-across-contexts"},"forbidden_claims":{"type":"array","minItems":1,"items":{"type":"string"}},"station_owner":{"const":"Dome-World"},"authority":{"type":"object","required":["automatic_station_advance","automatic_ash_action","human_closure_required"],"properties":{"automatic_station_advance":{"const":false},"automatic_ash_action":{"const":false},"human_closure_required":{"const":true}},"additionalProperties":false},"closure":{"type":"object","required":["status"],"properties":{"status":{"const":"OPEN"}},"additionalProperties":true}}}
