{"$schema":"https://json-schema.org/draft/2020-12/schema","$id":"td613.hush.phase6.hash-replay/v1","title":"Phase 6 Hash Replay","type":"object","required":["schema","packet_hash_sha256","hash_topology_packet_hash_sha256","packet_hashes_agree","section_hashes","section_replay_status","hash_only_packet_blocked","status"],"properties":{"schema":{"const":"td613.hush.phase6.hash-replay/v1"},"packet_hash_sha256":{"type":["string","null"],"pattern":"^sha256:[a-fA-F0-9]{64}$"},"hash_topology_packet_hash_sha256":{"type":["string","null"],"pattern":"^sha256:[a-fA-F0-9]{64}$"},"packet_hashes_agree":{"type":"boolean"},"section_hashes":{"type":"object"},"section_replay_status":{"enum":["passed","failed","not_run"]},"hash_only_packet_blocked":{"const":true},"status":{"enum":["passed","failed","not_run"]}},"additionalProperties":true}
